<!DOCTYPE ui:UiBinder SYSTEM "http://dl.google.com/gwt/DTD/xhtml.ent">
<ui:UiBinder xmlns:ui="urn:ui:com.google.gwt.uibinder"
	xmlns:g="urn:import:com.google.gwt.user.client.ui">
	<ui:style>
	
	</ui:style>
	<g:HTMLPanel>
		<g:VerticalPanel height="198px" width="142px">
			<g:Label text="Brugernavn:"/>
			<g:TextBox/>
			<g:Label text="Adgangskode"/>
			<g:TextBox/>
			<g:Label text="Saldo"/>
			<g:TextBox/>
			<g:HorizontalPanel>
				<g:Button ui:field="createUserBtn">Opret</g:Button>
				<g:Button ui:field="btnCancel" text="Annuller">Anuller</g:Button>
			</g:HorizontalPanel>
		</g:VerticalPanel>
	</g:HTMLPanel>
</ui:UiBinder> 